setup.py
cache_throttle/__init__.py
cache_throttle/decorators.py
cache_throttle/utils.py
django_cache_throttle.egg-info/PKG-INFO
django_cache_throttle.egg-info/SOURCES.txt
django_cache_throttle.egg-info/dependency_links.txt
django_cache_throttle.egg-info/requires.txt
django_cache_throttle.egg-info/top_level.txt
sample_project/__init__.py
sample_project/settings.py
sample_project/urls.py
sample_project/views.py
sample_project/wsgi.py