Metadata-Version: 1.1
Name: django-cache-throttle
Version: 2012.11.09.3
Summary: Cache-based rate-limiting for Django.
Home-page: https://github.com/bradbeattie/django-cache-throttle
Author: Brad Beattie
Author-email: bradbeattie@gmail.com
License: BSD
Platform: UNKNOWN
Classifier: Development Status :: 4 - Beta
Classifier: Environment :: Web Environment
Classifier: Framework :: Django
Classifier: Intended Audience :: Developers
Classifier: License :: OSI Approved :: BSD License
Classifier: Operating System :: OS Independent
Classifier: Programming Language :: Python
Classifier: Topic :: Software Development :: Libraries :: Python Modules
